agcounts/__init__.py
agcounts/extract.py
agcounts/legacy.py
agcounts/pow2.py
agcounts-0.2.6.dist-info/LICENSE
agcounts-0.2.6.dist-info/WHEEL
agcounts-0.2.6.dist-info/METADATA
agcounts-0.2.6.dist-info/RECORD
