Metadata-Version: 2.1
Name: agcounts
Version: 0.2.6
Summary: This project contains code to generate activity counts from accelerometer data.
Home-page: https://github.com/actigraph/agcounts
License: GPL-3.0-or-later
Author: Actigraph LLC
Author-email: data.science@theactigraph.com
Maintainer: Ali Neishabouri
Maintainer-email: ali.neishabouri@theactigraph.com
Requires-Python: >=3.8.1,<3.13
Classifier: License :: OSI Approved :: GNU General Public License v3 or later (GPLv3+)
Classifier: Programming Language :: Python :: 3
Classifier: Programming Language :: Python :: 3.9
Classifier: Programming Language :: Python :: 3.10
Requires-Dist: mne (>=1.4.0)
Requires-Dist: numpy (>=1.23.3)
Requires-Dist: pandas (>=1.2.5)
Requires-Dist: scipy (>=1.7.3)
Project-URL: Repository, https://github.com/actigraph/agcounts
